entry.py
app/__init__.py
app/__main__.py
app/reliable.py
gauss_linear-0.5.0.dist-info/LICENSE
gauss_linear-0.5.0.dist-info/METADATA
gauss_linear-0.5.0.dist-info/WHEEL
gauss_linear-0.5.0.dist-info/entry_points.txt
gauss_linear-0.5.0.dist-info/top_level.txt
gauss_linear-0.5.0.dist-info/RECORD
