Metadata-Version: 2.1
Name: gauss-linear
Version: 0.5.0
Summary: A simple command line tool to do linear algebra
Home-page: https://github.com/22raor/gauss
Author: Rishi Rao
Author-email: rao068048@gmail.com
License: MIT License
Classifier: Programming Language :: Python :: 3.8
Classifier: Operating System :: OS Independent
Requires-Python: >=3.8
License-File: LICENSE
Requires-Dist: sympy >=1.10
